Workbook
Name ACTION: #REF!
Name ACTION: #REF!

Sheet Cover
B2: SYSTEM TEST REPORT DOCUMENT
A4: Project Name | B4: Clawbot | E4: Creator | F4: <Creator>
A5: Project Code | B5: CLAWBOT | E5: Issue Date | F5: 46244.708
A6: Document Code | B6: =B5&"_"&"XXX"&"_"&"vx.x" -> CLAWBOT_XXX_vx.x | E6: Version | F6: v1.0
A9: Record of change
A10: Effective Date | B10: Version | C10: Change Item | D10: *A,D,M | E10: Change description | F10: Reference
A11: 46244.708 | B11: v1.0 | C11: System Test Report | D11: A | E11: Initial version

Sheet Test Cases
D1: TEST CASE LIST
B3: Project Name | D3: =Cover!B4 -> Clawbot
B4: Project Code | D4: =Cover!B5 -> CLAWBOT
B5: Test Environment Setup Description | D5: 1. Frontend: React + Vite (localhost:15876) 2. API Backend: .NET 8 (localhost:15874) 3. AgentService gRPC (localhost:15875) 4. Gateway: .NET 10 Ocelot (localhost:15873) 5. SQL Server 2022 (Docker :1433) 6. Redis 7 (Docker :6379) 7. Qdrant (Docker :6333) 8. MinIO (Docker :9001) 9. RabbitMQ (Docker :15672)
B8: No | C8: Function Name | D8: Sheet Name | E8: Description | F8: Pre-Condition
B9: 1 | C9: Tenant onboarding and initial configuration | D9: WF01 Onboarding | E9: Create a new tenant, configure an LLM provider, connect a channel, grant roles and verify the first sign-in and permission fence | F9: The full stack is running (all services up); an admin seed account exists
B10: 2 | C10: End-to-end auto-reply, handover and lead creation | D10: WF02 Auto-reply | E10: Receive an inbound message, answer it automatically using the knowledge base, pause when a sales agent intervenes, resume after the pause window, and create a scored lead from the conversation | F10: A channel is connected; a knowledge base is deployed; auto-reply is enabled on the test conversation
B11: 3 | C11: Recovery from job failures, queue outages and KB deploy errors | D11: WF03 Incident Recovery | E11: Failed background jobs are retried and logged; message queue outages do not lose messages; a KB deploy failure leaves the previous version active and is surfaced in the error log | F11: Hangfire job scheduler and RabbitMQ are running; the system error log tab is accessible
B12: 4 | C12: WF04 Lead Pipeline | D12: WF04 Lead Pipeline | F12: The full stack is running (all services up); an admin seed account exists; lead scoring rules are seeded via POST /api/lead-scoring-rules/seed-defaults
B13: 5 | C13: WF05 Content Pipeline | D13: WF05 Content Pipeline | F13: The full stack is running (all services up); a configured LLM provider is active; a deployed KB module exists for RAG context

Sheet Test Statistics
B1: TEST STATISTICS
B3: Project Name | C3: Clawbot | E3: Creator | G3: <Creator>
B4: Project Code | C4: CLAWBOT | E4: Reviewer/Approver
B5: Document Code | C5: =C4&"_"&"Test Report"&"_"&"vx.x" -> CLAWBOT_Test Report_vx.x | E5: Issue Date | H5: 46244.708
B6: Notes | C6: WF01 Onboarding, WF02 Auto-reply, WF03 Incident Recovery, WF04 Lead Pipeline, WF05 Content Pipeline
B10: No | C10: Module code | D10: Passed | E10: Failed | F10: Pending | G10: N/A | H10: Number of test cases
B11: 1 | C11: ='WF01 Onboarding'!B2 -> Tenant onboarding and initial configuration | D11: ='WF01 Onboarding'!B6 -> 0 | E11: ='WF01 Onboarding'!C6 -> 0 | F11: ='WF01 Onboarding'!D6 -> 7 | G11: ='WF01 Onboarding'!E6 -> 0 | H11: ='WF01 Onboarding'!B4 -> 7
B12: 2 | C12: ='WF02 Auto-reply'!B2 -> End-to-end auto-reply, handover and lead creation | D12: ='WF02 Auto-reply'!B6 -> 0 | E12: ='WF02 Auto-reply'!C6 -> 0 | F12: ='WF02 Auto-reply'!D6 -> 9 | G12: ='WF02 Auto-reply'!E6 -> 0 | H12: ='WF02 Auto-reply'!B4 -> 9
B13: 3 | C13: ='WF03 Incident Recovery'!B2 -> Recovery from job failures, queue outages and KB deploy errors | D13: ='WF03 Incident Recovery'!B6 -> 0 | E13: ='WF03 Incident Recovery'!C6 -> 0 | F13: ='WF03 Incident Recovery'!D6 -> 7 | G13: ='WF03 Incident Recovery'!E6 -> 0 | H13: ='WF03 Incident Recovery'!B4 -> 7
B14: 4 | C14: ='WF04 Lead Pipeline'!B2 -> WF04 Lead Pipeline | D14: ='WF04 Lead Pipeline'!B6 -> 0 | E14: ='WF04 Lead Pipeline'!C6 -> 0 | F14: ='WF04 Lead Pipeline'!D6 -> 8 | G14: ='WF04 Lead Pipeline'!E6 -> 0 | H14: ='WF04 Lead Pipeline'!B4 -> 8
B15: 5 | C15: ='WF05 Content Pipeline'!B2 -> WF05 Content Pipeline | D15: ='WF05 Content Pipeline'!B6 -> 0 | E15: ='WF05 Content Pipeline'!C6 -> 0 | F15: ='WF05 Content Pipeline'!D6 -> 8 | G15: ='WF05 Content Pipeline'!E6 -> 0 | H15: ='WF05 Content Pipeline'!B4 -> 8
C17: Sub total | D17: =SUM(D11:D15) -> 0 | E17: =SUM(E11:E15) -> 0 | F17: =SUM(F11:F15) -> 39 | G17: =SUM(G11:G15) -> 0 | H17: =SUM(H11:H15) -> 39
C19: Test coverage | E19: =(D17+E17)*100/(H17-G17) -> 0 | F19: %
C20: Test successful coverage | E20: =D17*100/(H17-G17) -> 0 | F20: %

Sheet WF01 Onboarding
A2: Workflow | B2: Tenant onboarding and initial configuration | R2: Passed
A3: Test requirement | B3: Create a new tenant, configure an LLM provider, connect a channel, grant roles and verify the first sign-in and permission fence | R3: Failed
A4: Number of TCs | B4: =COUNTIF($A$12:$A$1000,"TC-*") -> 7 | R4: Pending
A5: Testing Round | B5: Passed | C5: Failed | D5: Pending | E5: N/A | R5: N/A
A6: Round 1 | B6: =COUNTIF($F10:$F999,B5) -> 0 | C6: =COUNTIF($F10:$F999,C5) -> 0 | D6: =COUNTIF($F10:$F999,D5) -> 7 | E6: =COUNTIF($F10:$F999,E5) -> 0
A7: Round 2 | B7: =COUNTIF($I10:$I998,B5) -> 0 | C7: =COUNTIF($I10:$I998,C5) -> 0 | D7: =COUNTIF($I10:$I998,D5) -> 7 | E7: =COUNTIF($I10:$I998,E5) -> 0
A8: Round 3 | B8: =COUNTIF($L10:$L998,B5) -> 0 | C8: =COUNTIF($L10:$L998,C5) -> 0 | D8: =COUNTIF($L10:$L998,D5) -> 7 | E8: =COUNTIF($L10:$L998,E5) -> 0
A10: Test Case ID | B10: Test Case Description | C10: Test Case Procedure | D10: Expected Results | E10: Pre-conditions | F10: Round 1 | G10: Test date | H10: Tester | I10: Round 2 | J10: Test date | K10: Tester | L10: Round 3 | M10: Test date | N10: Tester | O10: Note
A11: Tenant and user setup
A12: TC-ST-ONB-001 | B12: Create a new tenant from the admin panel | C12: 1. Sign in as system admin. 2. Open system settings and create a new tenant with a unique name. | D12: The tenant is created and visible in the tenant list with status active. | E12: System admin account is seeded | F12: Pending | I12: Pending | L12: Pending
A13: TC-ST-ONB-002 | B13: Create the first admin user for the new tenant | C13: 1. Open the new tenant. 2. Create an admin user account with a temporary password. | D13: The user is created; a welcome email is sent; the user can sign in. | E13: The tenant was created in TC-ST-ONB-001 | F13: Pending | I13: Pending | L13: Pending
A14: TC-ST-ONB-003 | B14: Sign in as the new tenant admin and change the temporary password | C14: 1. Sign in with the temporary password. 2. Follow the password-change prompt. 3. Sign in again with the new password. | D14: Password change succeeds; the temporary password is no longer accepted; the dashboard loads. | E14: TC-ST-ONB-002 has been completed | F14: Pending | I14: Pending | L14: Pending
A15: TC-ST-ONB-004 | B15: Navigation menu reflects the granted role permissions | C15: 1. Create a user with a restricted role (conversations:read only). 2. Sign in as that user. | D15: Only the Inbox section is visible; /leads, /content, /kb, /agents are inaccessible. | E15: A restricted role has been created and granted | F15: Pending | I15: Pending | L15: Pending
A16: LLM provider configuration
A17: TC-ST-ONB-005 | B17: Configure an LLM provider with a valid API key | C17: 1. Open LLM Providers (/llm-providers). 2. Add a provider (e.g. OpenAI) with a valid API key. 3. Save and run the connection test. | D17: Provider is saved; connection test returns success; status shows active. | E17: A valid API key is available in the test environment | F17: Pending | I17: Pending | L17: Pending
A18: TC-ST-ONB-006 | B18: Reject an LLM provider URL that points to a private host without a grant | C18: 1. Attempt to save an LLM provider with baseUrl = http://192.168.1.10:8080. 2. Submit without enabling private host access. | D18: Save is rejected with an SSRF-guard error; no provider row is persisted. | E18: allowPrivateHosts is false (default) | F18: Pending | I18: Pending | L18: Pending
A19: Channel connection
A20: TC-ST-ONB-007 | B20: Connect a Facebook channel and verify the first message sync | C20: 1. Open system channels (/system/channels). 2. Connect a Facebook page with a valid token. 3. Wait for the initial sync. | D20: Channel shows as connected; existing conversations appear in /conversations within a few minutes. | E20: A Facebook test page and valid token are available | F20: Pending | I20: Pending | L20: Pending

Sheet WF02 Auto-reply
A2: Workflow | B2: End-to-end auto-reply, handover and lead creation | R2: Passed
A3: Test requirement | B3: Receive an inbound message, answer it automatically using the knowledge base, pause when a sales agent intervenes, resume after the pause window, and create a scored lead from the conversation | R3: Failed
A4: Number of TCs | B4: =COUNTIF($A$12:$A$1000,"TC-*") -> 9 | R4: Pending
A5: Testing Round | B5: Passed | C5: Failed | D5: Pending | E5: N/A | R5: N/A
A6: Round 1 | B6: =COUNTIF($F10:$F1001,B5) -> 0 | C6: =COUNTIF($F10:$F1001,C5) -> 0 | D6: =COUNTIF($F10:$F1001,D5) -> 9 | E6: =COUNTIF($F10:$F1001,E5) -> 0
A7: Round 2 | B7: =COUNTIF($I10:$I998,B5) -> 0 | C7: =COUNTIF($I10:$I998,C5) -> 0 | D7: =COUNTIF($I10:$I998,D5) -> 9 | E7: =COUNTIF($I10:$I998,E5) -> 0
A8: Round 3 | B8: =COUNTIF($L10:$L998,B5) -> 0 | C8: =COUNTIF($L10:$L998,C5) -> 0 | D8: =COUNTIF($L10:$L998,D5) -> 9 | E8: =COUNTIF($L10:$L998,E5) -> 0
A10: Test Case ID | B10: Test Case Description | C10: Test Case Procedure | D10: Expected Results | E10: Pre-conditions | F10: Round 1 | G10: Test date | H10: Tester | I10: Round 2 | J10: Test date | K10: Tester | L10: Round 3 | M10: Test date | N10: Tester | O10: Note
A11: Automatic answering
A12: TC-ST-ARP-001 | B12: Receive an inbound message and get an automatic reply | C12: 1. Send a message from the test channel that matches a KB topic. 2. Wait up to 30 seconds. | D12: An automatic outbound reply is sent; the reply text reflects the KB content. | E12: Auto-reply is enabled; KB is deployed and indexed | F12: Pending | I12: Pending | L12: Pending
A13: TC-ST-ARP-002 | B13: Decline to answer when no KB content covers the question | C13: 1. Send a message on a topic completely outside the KB. 2. Wait up to 30 seconds. | D13: The auto-reply sends a safe fallback message and optionally escalates to a human agent. | E13: Auto-reply is enabled; the question is outside all KB modules | F13: Pending | I13: Pending | L13: Pending
A14: TC-ST-ARP-003 | B14: Deduplicate a message delivered by both webhook and polling | C14: 1. Enable both ingestion paths. 2. Send a single message from the channel. | D14: Exactly one auto-reply is sent; exactly one message record is stored. | E14: Both ingestion paths are active | F14: Pending | I14: Pending | L14: Pending
A15: Handover to sales agent
A16: TC-ST-ARP-004 | B16: A manual reply by a sales agent pauses auto-reply | C16: 1. Sign in as a sales agent. 2. Send a manual reply on the conversation. 3. Send a new inbound message from the channel. | D16: Auto-reply stays silent for the configured pause window (default 5 minutes). | E16: Auto-reply is enabled on the conversation | F16: Pending | I16: Pending | L16: Pending
A17: TC-ST-ARP-005 | B17: Auto-reply resumes after the pause window without manual action | C17: 1. Trigger a pause by sending a manual reply. 2. Advance time past the pause window (or wait). 3. Send a new inbound message. | D17: The sweep job re-enables auto-reply; the new message gets an automatic response. | E17: A pause was triggered; the TryResumeAiAutoReply sweep job is running | F17: Pending | I17: Pending | L17: Pending
A18: TC-ST-ARP-006 | B18: Manually disabling auto-reply prevents automatic resumption | C18: 1. Toggle auto-reply OFF via the conversation UI. 2. Advance time past the default pause window. 3. Send a new inbound message. | D18: Auto-reply remains disabled (resume_at is null); no automatic response is sent. | E18: Auto-reply was explicitly toggled off | F18: Pending | I18: Pending | L18: Pending
A19: Lead creation from conversation
A20: TC-ST-ARP-007 | B20: Create a lead from a conversation and verify the initial score | C20: 1. Open a conversation that has contact details. 2. Create a lead from the conversation panel. 3. Inspect the lead score on /leads. | D20: Lead is created; score is calculated based on the lead scoring rules; pipeline stage reflects the score (cold / warm / hot). | E20: The conversation has an identifiable contact; lead scoring rules are seeded | F20: Pending | I20: Pending | L20: Pending
A21: TC-ST-ARP-008 | B21: Lead score increases when a purchase-intent event is recorded | C21: 1. Open the lead created in TC-ST-ARP-007. 2. Record a purchase_intent activity. 3. Refresh the lead card. | D21: The lead score increases by the purchase_intent delta (default +20); pipeline stage may advance. | E21: TC-ST-ARP-007 completed; lead is in cold or warm stage | F21: Pending | I21: Pending | L21: Pending
A22: TC-ST-ARP-009 | B22: Reactivate a lost lead when new inbound activity arrives | C22: 1. Mark a lead as lost. 2. Send a new inbound message from the same contact. | D22: The lead is reactivated; LastActivityAt is updated; the lost status is cleared. | E22: A lost lead exists for the contact | F22: Pending | I22: Pending | L22: Pending

Sheet WF03 Incident Recovery
A2: Workflow | B2: Recovery from job failures, queue outages and KB deploy errors | R2: Passed
A3: Test requirement | B3: Failed background jobs are retried and logged; message queue outages do not lose messages; a KB deploy failure leaves the previous version active and is surfaced in the error log | R3: Failed
A4: Number of TCs | B4: =COUNTIF($A$12:$A$1000,"TC-*") -> 7 | R4: Pending
A5: Testing Round | B5: Passed | C5: Failed | D5: Pending | E5: N/A | R5: N/A
A6: Round 1 | B6: =COUNTIF($F10:$F999,B5) -> 0 | C6: =COUNTIF($F10:$F999,C5) -> 0 | D6: =COUNTIF($F10:$F999,D5) -> 7 | E6: =COUNTIF($F10:$F999,E5) -> 0
A7: Round 2 | B7: =COUNTIF($I10:$I998,B5) -> 0 | C7: =COUNTIF($I10:$I998,C5) -> 0 | D7: =COUNTIF($I10:$I998,D5) -> 7 | E7: =COUNTIF($I10:$I998,E5) -> 0
A8: Round 3 | B8: =COUNTIF($L10:$L998,B5) -> 0 | C8: =COUNTIF($L10:$L998,C5) -> 0 | D8: =COUNTIF($L10:$L998,D5) -> 7 | E8: =COUNTIF($L10:$L998,E5) -> 0
A10: Test Case ID | B10: Test Case Description | C10: Test Case Procedure | D10: Expected Results | E10: Pre-conditions | F10: Round 1 | G10: Test date | H10: Tester | I10: Round 2 | J10: Test date | K10: Tester | L10: Round 3 | M10: Test date | N10: Tester | O10: Note
A11: Background job failure and retry
A12: TC-ST-REC-001 | B12: A Hangfire job that fails is retried the configured number of times | C12: 1. Inject a transient failure into a job handler. 2. Observe the Hangfire dashboard or job logs. | D12: The job is retried up to the configured retry count, then marked as failed with the error recorded. | E12: Retry count is configured; Hangfire dashboard is accessible | F12: Pending | I12: Pending | L12: Pending
A13: TC-ST-REC-002 | B13: A failed job appears in the system error log | C13: 1. Let a job fail permanently (exhaust retries). 2. Open the error log tab (/logs). | D13: The failure entry is listed with its exception type, message and timestamp. | E13: TC-ST-REC-001 has been completed | F13: Pending | I13: Pending | L13: Pending
A14: TC-ST-REC-003 | B14: A Hangfire job runs in an isolated DI scope with the correct tenant context | C14: 1. Trigger a scheduled job for a specific tenant. 2. Verify the job reads and writes data only for that tenant. | D14: No cross-tenant data contamination; ITenantOwned query filters are applied. | E14: Two tenant accounts with overlapping data exist | F14: Pending | I14: Pending | L14: Pending
A15: Message queue outage
A16: TC-ST-REC-004 | B16: Messages queued during a consumer outage are processed after restart | C16: 1. Stop the RabbitMQ consumer service. 2. Send three inbound messages from the channel. 3. Start the consumer again. | D16: All three messages are ingested in order after the consumer restarts; none is lost. | E16: RabbitMQ queue durability is enabled | F16: Pending | I16: Pending | L16: Pending
A17: TC-ST-REC-005 | B17: A duplicate message delivered by a second consumer instance is not processed twice | C17: 1. Start a second consumer instance. 2. Deliver one inbound message to the queue. | D17: Only one consumer processes the message; no duplicate reply is sent. | E17: RabbitMQ is configured with exclusive consumer or logical dedup | F17: Pending | I17: Pending | L17: Pending
A18: KB deploy failure
A19: TC-ST-REC-006 | B19: A KB deploy failure leaves the previously deployed version active | C19: 1. Deploy a version while Qdrant is unavailable. 2. Check which version is active after the deploy job fails. | D19: The deploy job fails and is logged; the previous deployed version remains active for retrieval. | E19: A deployed version exists; Qdrant can be temporarily stopped | F19: Pending | I19: Pending | L19: Pending
A20: TC-ST-REC-007 | B20: KB deploy retries succeed once the vector store recovers | C20: 1. Restore Qdrant after it was stopped in TC-ST-REC-006. 2. Re-trigger the deploy job. | D20: The deploy job completes successfully; the new version becomes active. | E20: TC-ST-REC-006 completed; Qdrant is restored | F20: Pending | I20: Pending | L20: Pending

Sheet WF04 Lead Pipeline
A2: Workflow | B2: WF04 Lead Pipeline | R2: Passed
A3: Test requirement | R3: Failed
A4: Number of TCs | B4: =COUNTIF($A$12:$A$1000,"TC-*") -> 8 | R4: Pending
A5: Testing Round | B5: Passed | C5: Failed | D5: Pending | E5: N/A | R5: N/A
A6: Round 1 | B6: =COUNTIF($F10:$F1000,B5) -> 0 | C6: =COUNTIF($F10:$F1000,C5) -> 0 | D6: =COUNTIF($F10:$F1000,D5) -> 8 | E6: =COUNTIF($F10:$F1000,E5) -> 0
A7: Round 2 | B7: =COUNTIF($I10:$I998,B5) -> 0 | C7: =COUNTIF($I10:$I998,C5) -> 0 | D7: =COUNTIF($I10:$I998,D5) -> 8 | E7: =COUNTIF($I10:$I998,E5) -> 0
A8: Round 3 | B8: =COUNTIF($L10:$L998,B5) -> 0 | C8: =COUNTIF($L10:$L998,C5) -> 0 | D8: =COUNTIF($L10:$L998,D5) -> 8 | E8: =COUNTIF($L10:$L998,E5) -> 0
A10: Test Case ID | B10: Test Case Description | C10: Test Case Procedure | D10: Expected Results | E10: Pre-conditions | F10: Round 1 | G10: Test date | H10: Tester | I10: Round 2 | J10: Test date | K10: Tester | L10: Round 3 | M10: Test date | N10: Tester | O10: Note
A11: Lead creation and initial scoring
A12: TC-ST-LP-001 | B12: A new conversation from Facebook creates a lead in cold stage | C12: 1. Simulate an inbound Facebook message. 2. Allow the auto-reply and lead-creation agent to run. 3. GET /api/leads and filter by contactId. | D12: A lead is created with stage=cold and score=0; the contact is linked. | E12: No existing lead for the contact | F12: Pending | I12: Pending | L12: Pending
A13: TC-ST-LP-002 | B13: Score advances the lead from cold to warm after price inquiry activities | C13: 1. Record asked_price and fast_reply activities via POST /api/leads/{id}/activities. 2. GET /api/leads/{id}. | D13: score >= 30; stage=warm. | E13: Lead is in cold stage; scoring rules are seeded | F13: Pending | I13: Pending | L13: Pending
A14: Stage advancement and manual override
A15: TC-ST-LP-003 | B15: Enough purchase-intent signals advance the lead to hot | C15: 1. Record purchase_intent activities until score >= 70. 2. GET /api/leads/{id}. | D15: stage=hot; score >= 70. | E15: Lead is in warm stage | F15: Pending | I15: Pending | L15: Pending
A16: TC-ST-LP-004 | B16: A sales agent manually moves a hot lead to won | C16: 1. POST /api/leads/{id}/stage with stage=won. | D16: HTTP 200; stage=won; WonAt timestamp is set; the lead no longer appears in active pipeline views. | E16: Lead is in hot stage | F16: Pending | I16: Pending | L16: Pending
A17: TC-ST-LP-005 | B17: A hot lead is moved to lost and a reason is recorded | C17: 1. POST /api/leads/{id}/stage with stage=lost and reason. | D17: HTTP 200; stage=lost; LostReason is stored. | E17: Lead is in hot stage | F17: Pending | I17: Pending | L17: Pending
A18: Reactivation and forecast
A19: TC-ST-LP-006 | B19: A lost lead is reactivated when the customer sends a new message | C19: 1. Simulate an inbound message from the lost lead contact. 2. GET /api/leads/{id}. | D19: Lead status returns to active; LastActivityAt is updated; stage resets to warm (not cold). | E19: A lost lead exists; the contact has an active conversation channel | F19: Pending | I19: Pending | L19: Pending
A20: TC-ST-LP-007 | B20: Forecast shows the correct count and estimated value for hot leads | C20: 1. GET /api/leads/forecast. | D20: Response includes hot lead count and summed estimated value; numbers match the current database state. | E20: At least two leads are in hot stage | F20: Pending | I20: Pending | L20: Pending
A21: TC-ST-LP-008 | B21: Re-scoring all leads after a rule change updates stages in bulk | C21: 1. Update the purchase_intent delta via PUT /api/lead-scoring-rules/{id}. 2. POST /api/leads/rescore-all. | D21: All affected leads have their scores and stages recalculated; no leads are left with a stale score. | E21: Multiple leads with purchase_intent activities exist | F21: Pending | I21: Pending | L21: Pending

Sheet WF05 Content Pipeline
A2: Workflow | B2: WF05 Content Pipeline | R2: Passed
A3: Test requirement | R3: Failed
A4: Number of TCs | B4: =COUNTIF($A$12:$A$1000,"TC-*") -> 8 | R4: Pending
A5: Testing Round | B5: Passed | C5: Failed | D5: Pending | E5: N/A | R5: N/A
A6: Round 1 | B6: =COUNTIF($F10:$F1000,B5) -> 0 | C6: =COUNTIF($F10:$F1000,C5) -> 0 | D6: =COUNTIF($F10:$F1000,D5) -> 8 | E6: =COUNTIF($F10:$F1000,E5) -> 0
A7: Round 2 | B7: =COUNTIF($I10:$I998,B5) -> 0 | C7: =COUNTIF($I10:$I998,C5) -> 0 | D7: =COUNTIF($I10:$I998,D5) -> 8 | E7: =COUNTIF($I10:$I998,E5) -> 0
A8: Round 3 | B8: =COUNTIF($L10:$L998,B5) -> 0 | C8: =COUNTIF($L10:$L998,C5) -> 0 | D8: =COUNTIF($L10:$L998,D5) -> 8 | E8: =COUNTIF($L10:$L998,E5) -> 0
A10: Test Case ID | B10: Test Case Description | C10: Test Case Procedure | D10: Expected Results | E10: Pre-conditions | F10: Round 1 | G10: Test date | H10: Tester | I10: Round 2 | J10: Test date | K10: Tester | L10: Round 3 | M10: Test date | N10: Tester | O10: Note
A11: Brief creation and AI generation
A12: TC-ST-CP-001 | B12: A content brief triggers AI generation and produces a draft item | C12: 1. POST /api/content/briefs with platform=facebook and topic. 2. POST /api/content/items/generate with the briefId. 3. Poll until item status=draft. | D12: A content item with a non-empty body is created in draft status within 60 seconds. | E12: LLM provider responds within the configured timeout | F12: Pending | I12: Pending | L12: Pending
A13: TC-ST-CP-002 | B13: Lint blocks a draft that contains an absolute guarantee phrase | C13: 1. Generate a draft using a stub that returns a body containing the phrase "100% guaranteed". 2. Check item status. | D13: Item status=needs_human; lint error code is reported. | E13: LLM stub is configured; ContentLint is enabled | F13: Pending | I13: Pending | L13: Pending
A14: Review and approval
A15: TC-ST-CP-003 | B15: Agent reviewer approves a clean draft and it becomes ready for human approval | C15: 1. Wait for the reviewer agent run to complete on the draft item. 2. GET /api/content/items/{id}. | D15: AgentReviewStatus=passed; item is in the human approval queue. | E15: Reviewer agent is bound to an LLM provider; draft item is clean | F15: Pending | I15: Pending | L15: Pending
A16: TC-ST-CP-004 | B16: A human approves the item and it becomes approved | C16: 1. POST /api/content/items/{id}/approve. | D16: HTTP 200; status=approved; ApprovedAt and ApprovedBy are recorded. | E16: Item has passed agent review | F16: Pending | I16: Pending | L16: Pending
A17: TC-ST-CP-005 | B17: A human rejects a draft and provides a reason | C17: 1. POST /api/content/items/{id}/reject with reason="off-brand tone". | D17: HTTP 200; status=rejected; RejectedReason=off-brand tone. | E17: Item is in draft or needs_human state | F17: Pending | I17: Pending | L17: Pending
A18: Scheduling and repurpose
A19: TC-ST-CP-006 | B19: An approved item is scheduled for the Facebook golden hour | C19: 1. Calculate the next Facebook golden hour (20:30 VN time). 2. POST /api/content/items/{id}/schedule with publishAt set to that time. | D19: HTTP 200; status=scheduled; publishAt matches the golden hour. | E19: Item is approved | F19: Pending | I19: Pending | L19: Pending
A20: TC-ST-CP-007 | B20: A published item is repurposed for TikTok | C20: 1. POST /api/content/items/{id}/repurpose with targetPlatform=tiktok. | D20: HTTP 202; a new draft item is created for tiktok; the original item status is unchanged. | E20: A published item exists; a brief for tiktok exists | F20: Pending | I20: Pending | L20: Pending
A21: TC-ST-CP-008 | B21: Chain metrics are recorded after a successful publish | C21: 1. Trigger a simulated publish for the scheduled item. 2. GET /api/content/chain-metrics. | D21: A metric entry exists for the chain run; generation and review latencies are recorded. | E21: The mock publish adapter is active | F21: Pending | I21: Pending | L21: Pending
